{
  "parent": "minecraft:recipes/root",
  "rewards": {
    "recipes": [
      "charginggadgets:charging_station"
    ]
  },
  "criteria": {
    "has_diamonds": {
      "trigger": "minecraft:inventory_changed",
      "conditions": {
        "items": [
          {
            "tag": "forge:gems/diamond"
          }
        ]
      }
    },
    "has_the_recipe": {
      "trigger": "minecraft:recipe_unlocked",
      "conditions": {
        "recipe": "charginggadgets:charging_station"
      }
    }
  },
  "requirements": [
    [
      "has_diamonds",
      "has_the_recipe"
    ]
  ]
}